Metadata-Version: 2.1
Name: pyAtome
Version: 0.1.2
Summary: Get your energy consumption from Atome Linky device
Home-page: http://github.com/baqs/pyAtome/
Author: Pierre Ourdouille
Author-email: baqs@users.github.com
License: Apache Software License 2.0
Platform: UNKNOWN
License-File: LICENSE.md
